Assign_GUP/LICENSE
Assign_GUP/__init__.py
Assign_GUP/_version.py
Assign_GUP/about.py
Assign_GUP/agup_data.py
Assign_GUP/auto_assignment.py
Assign_GUP/editor_email_template.py
Assign_GUP/email_mvc_view.py
Assign_GUP/email_template.py
Assign_GUP/event_filters.py
Assign_GUP/general_mvc_model.py
Assign_GUP/history.py
Assign_GUP/main_window.py
Assign_GUP/plainTextEdit.py
Assign_GUP/prop_mvc_data.py
Assign_GUP/prop_mvc_view.py
Assign_GUP/prop_revu_grid.py
Assign_GUP/proposal.py
Assign_GUP/proposal_details.py
Assign_GUP/qt_utils.py
Assign_GUP/report_analysis_grid.py
Assign_GUP/report_assignments.py
Assign_GUP/report_summary.py
Assign_GUP/resources.py
Assign_GUP/reviewer.py
Assign_GUP/reviewer_details.py
Assign_GUP/revu_mvc_data.py
Assign_GUP/revu_mvc_view.py
Assign_GUP/settings.py
Assign_GUP/signals.py
Assign_GUP/tools.py
Assign_GUP/topic_slider.py
Assign_GUP/topics.py
Assign_GUP/topics_editor.py
Assign_GUP/xml_utility.py
Assign_GUP/resources/about.ui
Assign_GUP/resources/agup_review_session.xsd
Assign_GUP/resources/delete.bmp
Assign_GUP/resources/editor_email_template.ui
Assign_GUP/resources/email_template.txt
Assign_GUP/resources/emailview.ui
Assign_GUP/resources/listview.ui
Assign_GUP/resources/main_window.ui
Assign_GUP/resources/plainTextEdit.ui
Assign_GUP/resources/plus.bmp
Assign_GUP/resources/proposal_details.ui
Assign_GUP/resources/proposals.xsd
Assign_GUP/resources/reviewer_details.ui
Assign_GUP/resources/topics_editor.ui
Assign_GUP-2017.4.0.dist-info/DESCRIPTION.rst
Assign_GUP-2017.4.0.dist-info/METADATA
Assign_GUP-2017.4.0.dist-info/RECORD
Assign_GUP-2017.4.0.dist-info/WHEEL
Assign_GUP-2017.4.0.dist-info/entry_points.txt
Assign_GUP-2017.4.0.dist-info/metadata.json
Assign_GUP-2017.4.0.dist-info/top_level.txt
