Metadata-Version: 2.0
Name: Assign-GUP
Version: 2017.4.0
Summary: Assist in assigning APS GUPs to PRP members
Home-page: http://Assign_GUP.readthedocs.io
Author: Pete R. Jemian
Author-email: jemian@anl.gov
License: UChicago Argonne, LLC OPEN SOURCE LICENSE (see LICENSE file)
Download-URL: https://github.com/prjemian/assign_gup.git
Keywords: APS,GUP,PRP
Platform: any
Classifier: Development Status :: 5 - Production/Stable
Classifier: Environment :: Console
Classifier: Intended Audience :: Science/Research
Classifier: License :: Free To Use But Restricted
Classifier: Operating System :: OS Independent
Classifier: Programming Language :: Python
Classifier: Topic :: Scientific/Engineering
Classifier: Topic :: Utilities
Requires-Dist: lxml
Requires-Dist: pyRestTable
